{
  "translations":[
    {
      "sourceText": "Говорит попугай попугаю, Я тебя, попугай, попугаю.",
      "translatedText": "^ Says parrot ^ parrot, I'm ^ you, parrot, parrot.",
      "correctedText": "A parrot says to a parrot, I will scare you, parrot.",
      "hter":1,
      "sourceTags": [2,4,7],
      "transSubTags":[],
      "transDelTags":[],
      "transInsTags":[1,4],
      "transShiftTags":[1,3,7,10],
      "transPolyTags":[],
      "transHomoTags":[3,10],
      "transPerTags":[],
      "corrSubTags":[],
      "corrInsTags":[1,4,5],
      "corrShiftTags":[2],
      "tags": [6],
      "correctionTags":[7],
      "mappings":[[[2],[1,3],[2]],[[7],[7,10],[9]],[[4],[6],[7]],[[7],[7],[8]],[[],[1],[1]],[[],[4],[4,5]]],
      "lineNumber":57,
      "numCorrections":[1,5,1,1]
    },
    {
      "sourceText": "Попугай попугаю в ответ, Попугай, попугай, попугая.",
      "translatedText": "Parrot parrot in return,, ^ parrot, parrot, parrot.",
      "correctedText": "The parrot answers the parrot, parrot, scare the parrot",
      "hter":1,
      "sourceTags": [],
      "transSubTags":[],
      "transDelTags":[],
      "transInsTags":[],
      "transShiftTags":[],
      "transPolyTags":[],
      "transHomoTags":[],
      "transPerTags":[],
      "corrSubTags":[],
      "corrInsTags":[],
      "corrShiftTags":[],
      "tags": [],
      "correctionTags":[],
      "mappings":[],
      "lineNumber":58,
      "numCorrections":[3,2,0,1]
    }
  ]
}